textractor/__init__.py
textractor/textractor.py
latextractor-1.0.0.dist-info/LICENSE
latextractor-1.0.0.dist-info/METADATA
latextractor-1.0.0.dist-info/WHEEL
latextractor-1.0.0.dist-info/entry_points.txt
latextractor-1.0.0.dist-info/top_level.txt
latextractor-1.0.0.dist-info/RECORD
