Metadata-Version: 2.1
Name: latextractor
Version: 1.0.0
Summary: Extracting build-essential files from a LaTeX project and zip them.
Home-page: https://github.com/cburkert/textractor
Maintainer: Christian Burkert
Maintainer-email: textractor@cburkert.de
License: MIT
Keywords: tex,latex,zip
Platform: UNKNOWN
Classifier: Topic :: Software Development :: Version Control :: Git
Classifier: Programming Language :: Python :: 3
Classifier: Programming Language :: Python :: 3 :: Only
Classifier: Programming Language :: Python :: 3.6
Classifier: Programming Language :: Python :: 3.7
Classifier: Operating System :: OS Independent
Requires-Python: >=3.6
License-File: LICENSE
Requires-Dist: click (>=7)
